k3down2/__init__.py
k3down2/down2.py
k3down2/mime.py
k3down2/syntax_highlight.py
k3down2-0.1.22.dist-info/licenses/LICENSE
k3down2-0.1.22.dist-info/METADATA
k3down2-0.1.22.dist-info/WHEEL
k3down2-0.1.22.dist-info/top_level.txt
k3down2-0.1.22.dist-info/RECORD
